MANIFEST.in
README.rst
setup.py
kyber/__init__.py
kyber/default.css
kyber/main.py
kyber.egg-info/PKG-INFO
kyber.egg-info/SOURCES.txt
kyber.egg-info/dependency_links.txt
kyber.egg-info/entry_points.txt
kyber.egg-info/top_level.txt
kyber/parsers/__init__.py
kyber/parsers/functions.py
kyber/parsers/html.py
kyber/parsers/pageindex.py