Metadata-Version: 1.1
Name: kyber
Version: 0.1.0
Summary: A publishing toolchain for Confluence
Home-page: https://github.com/lamestation/kyber
Author: LameStation
Author-email: contact@lamestation.com
License: GPLv3
Keywords: confluence documentation generation wiki pdf html export space
Platform: UNKNOWN
Classifier: Environment :: Console
Classifier: Development Status :: 2 - Pre-Alpha
Classifier: Topic :: Utilities
Classifier: Topic :: Documentation
Classifier: Topic :: Software Development :: Documentation
Classifier: Topic :: Text Processing :: Markup
Classifier: Topic :: Text Processing :: Markup :: HTML
Classifier: Topic :: Utilities
Classifier: License :: OSI Approved :: GNU General Public License v3 (GPLv3)
Classifier: Programming Language :: Python :: 2 :: Only
Classifier: Programming Language :: Python :: 2.7
